mercury/__init__.py
mercury/app.py
mercury/__pycache__/__init__.cpython-310.pyc
mercury/__pycache__/app.cpython-310.pyc
mercury/controllers/notification.py
mercury/controllers/user.py
mercury/controllers/__pycache__/notification.cpython-310.pyc
mercury/controllers/__pycache__/user.cpython-310.pyc
mercury/models/user.py
mercury/models/__pycache__/user.cpython-310.pyc
mercury/services/auth.py
mercury/services/config.py
mercury/services/custom_exceptions.py
mercury/services/database_nosql_mongo.py
mercury/services/database_sql.py
mercury/services/dictionaries.py
mercury/services/notification.py
mercury/services/routes.py
mercury/services/signals.py
mercury/services/user.py
mercury/services/__pycache__/auth.cpython-310.pyc
mercury/services/__pycache__/config.cpython-310.pyc
mercury/services/__pycache__/custom_exceptions.cpython-310.pyc
mercury/services/__pycache__/database_nosql_mongo.cpython-310.pyc
mercury/services/__pycache__/database_sql.cpython-310.pyc
mercury/services/__pycache__/dictionaries.cpython-310.pyc
mercury/services/__pycache__/notification.cpython-310.pyc
mercury/services/__pycache__/routes.cpython-310.pyc
mercury/services/__pycache__/signals.cpython-310.pyc
mercury/services/__pycache__/user.cpython-310.pyc
mercury/services/tasks/__init__.py
mercury/services/tasks/__pycache__/__init__.cpython-310.pyc
mercury/services/tasks/notification/__init__.py
mercury/services/tasks/notification/__pycache__/__init__.cpython-310.pyc
mercury/static/favicon.ico
mercury_py-1.0.6.dist-info/LICENSE
mercury_py-1.0.6.dist-info/METADATA
mercury_py-1.0.6.dist-info/WHEEL
mercury_py-1.0.6.dist-info/top_level.txt
mercury_py-1.0.6.dist-info/RECORD
