Metadata-Version: 2.1
Name: mercury-py
Version: 1.0.6
Summary: mercury-py (Mercury for Python) is a Python based microservice that allow to manage scheduled notifications sending.
Home-page: https://github.com/CoffeePerry/mercury-py
Download-URL: https://github.com/CoffeePerry/mercury-py/archive/1.0.6.tar.gz
Author: Simone Perini
Author-email: perinisimone98@gmail.com
License: GPL-3.0
Keywords: notifications,authentication,email,sms,push notification,telegram
Classifier: Development Status :: 5 - Production/Stable
Classifier: Framework :: Flask
Classifier: Intended Audience :: Developers
Classifier: Natural Language :: English
Classifier: License :: OSI Approved :: GNU General Public License v3 (GPLv3)
Classifier: Operating System :: OS Independent
Classifier: Programming Language :: Python :: 3
Classifier: Topic :: Communications
Classifier: Topic :: Communications :: Email
Classifier: Topic :: Communications :: Email :: Email Clients (MUA)
Classifier: Topic :: Utilities
License-File: LICENSE
Requires-Dist: Flask (==2.2.2)
Requires-Dist: Flask-RESTful (==0.3.9)
Requires-Dist: Flask-SQLAlchemy (==3.0.3)
Requires-Dist: Flask-PyMongo (==2.3.0)
Requires-Dist: Flask-JWT-Extended (==4.4.4)
Requires-Dist: Flask-Mail (==0.9.1)
Requires-Dist: celery (==5.2.7)
